<DescribeInstancesResult xmlns="http://ec2.amazonaws.com/doc/2015-10-01">
  <reservationSet>
    <item>
      <reservationId>r-1234abcd</reservationId>
      <ownerId>012345678912</ownerId>
      <groupSet>
        <item>
          <groupId></groupId>
          <groupName></groupName>
        </item>
      </groupSet>
      <instancesSet>
        <item>
          <instanceId>i-1234abcd</instanceId>
          <imageId>ami-f80e0596</imageId>
          <instanceState>
          </instanceState>
          <privateDnsName>ip-192-168-0-120.ap-northeast-1.compute.internal</privateDnsName>
          <dnsName>ec2-92-173-8-101.ap-northeast-1.compute.amazonaws.com</dnsName>
          <reason></reason>
          <keyName>test-key</keyName>
          <amiLaunchIndex>0</amiLaunchIndex>
          <productCodes>
          </productCodes>
          <instanceType>t2.nano</instanceType>
          <launchTime>2016-04-24T17:51:35.000Z</launchTime>
          <placement>
          </placement>
          <kernelId></kernelId>
          <ramdiskId></ramdiskId>
          <platform>
          </platform>
          <monitoring>
          </monitoring>
          <subnetId>subnet-1234abcd</subnetId>
          <vpcId>vpc-1234abcd</vpcId>
          <privateIpAddress>192.168.0.120</privateIpAddress>
          <ipAddress>92.173.8.101</ipAddress>
          <stateReason>
          </stateReason>
          <architecture>
          </architecture>
          <rootDeviceType>
          </rootDeviceType>
          <rootDeviceName>/dev/xvda</rootDeviceName>
          <blockDeviceMapping>
          </blockDeviceMapping>
          <virtualizationType>
          </virtualizationType>
          <instanceLifecycle>
          </instanceLifecycle>
          <spotInstanceRequestId></spotInstanceRequestId>
          <clientToken>gdfKL0123456789123</clientToken>
          <tagSet>
          </tagSet>
          <groupSet>
          </groupSet>
          <sourceDestCheck>true</sourceDestCheck>
          <hypervisor>
          </hypervisor>
          <networkInterfaceSet>
          </networkInterfaceSet>
          <iamInstanceProfile>
          </iamInstanceProfile>
          <ebsOptimized>false</ebsOptimized>
          <sriovNetSupport></sriovNetSupport>
        </item>
      </instancesSet>
    </item>
  </reservationSet>
</DescribeInstancesResult>
